jikan4/__init__.py
jikan4/__version__.py
jikan4/aiojikan.py
jikan4/jikan.py
jikan4/models.py
jikan4/utils/__init__.py
jikan4/utils/async_limiter.py
jikan4/utils/limiter.py
tests/__init__.py
tests/test_aiojikan.py
tests/test_async_limit.py
tests/test_jikan.py
tests/test_limit.py
jikan4-0.2.1.dist-info/LICENSE
jikan4-0.2.1.dist-info/METADATA
jikan4-0.2.1.dist-info/WHEEL
jikan4-0.2.1.dist-info/top_level.txt
jikan4-0.2.1.dist-info/RECORD
