Metadata-Version: 2.1
Name: jikan4
Version: 0.2.1
Summary: A Python wrapper for the Jikan API
Home-page: https://github.com/mdabessa/jikan4
Author: Matheus Bessa
Keywords: jikan,jikan4,jikan-api,jikan4-api,jikan-wrapper,jikan4-wrapper,jikan4-python,jikan-python
Requires-Python: >=3.10
License-File: LICENSE
